canadacovidmetrics/__init__.py
canadacovidmetrics/canadacovidmetrics.py
canadacovidmetrics-0.2.5.dist-info/LICENSE.MD
canadacovidmetrics-0.2.5.dist-info/WHEEL
canadacovidmetrics-0.2.5.dist-info/METADATA
canadacovidmetrics-0.2.5.dist-info/RECORD
