Metadata-Version: 2.1
Name: canadacovidmetrics
Version: 0.2.5
Summary: This package enables obtain key metrics regarding covid situation in Canada
License: MIT
Author: Valli A
Requires-Python: >=3.9,<4.0
Classifier: License :: OSI Approved :: MIT License
Classifier: Programming Language :: Python :: 3
Classifier: Programming Language :: Python :: 3.10
Classifier: Programming Language :: Python :: 3.9
Requires-Dist: DateTime (>=4.3,<5.0)
Requires-Dist: pandas (>=1.3.5,<2.0.0)
Requires-Dist: pytest (>=6.2.5,<7.0.0)
Requires-Dist: requests (>=2.27.1,<3.0.0)
